LICENSE
README.md
setup.cfg
setup.py
cpfinder/__init__.py
cpfinder.egg-info/PKG-INFO
cpfinder.egg-info/SOURCES.txt
cpfinder.egg-info/dependency_links.txt
cpfinder.egg-info/requires.txt
cpfinder.egg-info/top_level.txt
cpfinder/datasets/__init__.py
cpfinder/eval_metrics/__init__.py
cpfinder/feature_engineering/__init__.py
cpfinder/methods/__init__.py
cpfinder/methods/online_changepoint_detection.py
cpfinder/methods/online_rulsif.py
cpfinder/utils/__init__.py
cpfinder/vis/__init__.py
cpfinder/vis/plot_mtp.py